monoai/__init__.py
monoai/agents/__init__.py
monoai/agents/agent.py
monoai/agents/agentic_loops/__init__.py
monoai/agents/agentic_loops/_agentic_loop.py
monoai/agents/agentic_loops/_function_calling_agentic_loop.py
monoai/agents/agentic_loops/_other_agentic_loops.py
monoai/agents/agentic_loops/_react_agentic_loop.py
monoai/application/__init__.py
monoai/application/application.py
monoai/application/rate_limiter.py
monoai/chat/__init__.py
monoai/chat/chat.py
monoai/chat/history.py
monoai/cli/__init__.py
monoai/conf/__init__.py
monoai/conf/conf.py
monoai/keys/keys_manager.py
monoai/mcp/__init__.py
monoai/mcp/_mcp_tool_parser.py
monoai/mcp/mcp_server.py
monoai/models/__init__.py
monoai/models/_base_model.py
monoai/models/_prompt_executor.py
monoai/models/_response_processor.py
monoai/models/auto_model.py
monoai/models/collaborative_model.py
monoai/models/hosted_model.py
monoai/models/image_model.py
monoai/models/model.py
monoai/models/multi_model.py
monoai/models/voice_model.py
monoai/observability/__init__.py
monoai/prompts/__init__.py
monoai/prompts/fewshot_prompt.py
monoai/prompts/iterative_prompt.py
monoai/prompts/meta_prompt.py
monoai/prompts/multi_prompt.py
monoai/prompts/prompt.py
monoai/prompts/prompt_chain.py
monoai/prompts/safe_prompt.py
monoai/prompts/system_prompt.py
monoai/rag/__init__.py
monoai/rag/documents_builder.py
monoai/rag/rag.py
monoai/rag/vectordb.py
monoai/tests/test_agent.py
monoai/tests/test_chat.py
monoai/tests/test_model.py
monoai/tokens/__init__.py
monoai/tokens/token_cost.py
monoai/tokens/token_counter.py
monoai/tokens/token_pricing.py
monoai/tools/__init__.py
monoai/tools/_tool_parser.py
monoai/tools/browser_use.py
monoai/tools/colab_downloader.py
monoai/tools/computer_use.py
monoai/tools/domain_whois.py
monoai/tools/webscraping.py
monoai/tools/websearch.py
monoai/ui/__init__.py
monoai/ui/ui.py
monoai-0.0.25.dist-info/licenses/LICENSE
monoai-0.0.25.dist-info/METADATA
monoai-0.0.25.dist-info/WHEEL
monoai-0.0.25.dist-info/entry_points.txt
monoai-0.0.25.dist-info/top_level.txt
monoai-0.0.25.dist-info/RECORD
