Metadata-Version: 2.4
Name: monoai
Version: 0.0.25
Summary: MonoAI - The complete framework to build AI-powered applications
Author-email: ProfessionAI Tech <tech@profession.ai>
Project-URL: Homepage, https://github.com/Profession-AI/MONOAI
Requires-Python: >=3.8
License-File: LICENSE
Requires-Dist: litellm
Requires-Dist: typing-extensions
Requires-Dist: xmltodict
Requires-Dist: pytest
Requires-Dist: typer
Requires-Dist: mcp
Dynamic: license-file
